MANIFEST.in
README.md
requirements.txt
setup.py
multi_realsense_manager/__info__.py
multi_realsense_manager/__init__.py
multi_realsense_manager/class_as_process.py
multi_realsense_manager/multi_realsense_manager.py
multi_realsense_manager/rs_utils.py
multi_realsense_manager.egg-info/PKG-INFO
multi_realsense_manager.egg-info/SOURCES.txt
multi_realsense_manager.egg-info/dependency_links.txt
multi_realsense_manager.egg-info/requires.txt
multi_realsense_manager.egg-info/top_level.txt